{
  "main": {
    "id": "c9996b632cd1652d",
    "type": "split",
    "children": [
      {
        "id": "f3d70d8c6d2b3df4",
        "type": "tabs",
        "children": [
          {
            "id": "850e2ae8dd7226b7",
            "type": "leaf",
            "state": {
              "type": "markdown",
              "state": {
                "file": "深度学习/计算机视觉.md",
                "mode": "source",
                "source": false
              }
            }
          }
        ]
      }
    ],
    "direction": "vertical"
  },
  "left": {
    "id": "d5ca1e46e7e2d0e3",
    "type": "split",
    "children": [
      {
        "id": "3b4ddabccfdc595c",
        "type": "tabs",
        "dimension": 80.32305433186491,
        "children": [
          {
            "id": "03e03384561a4479",
            "type": "leaf",
            "state": {
              "type": "file-explorer",
              "state": {
                "sortOrder": "alphabetical"
              }
            }
          },
          {
            "id": "2ac6af0cc51e1844",
            "type": "leaf",
            "state": {
              "type": "search",
              "state": {
                "query": "",
                "matchingCase": false,
                "explainSearch": false,
                "collapseAll": false,
                "extraContext": false,
                "sortOrder": "alphabetical"
              }
            }
          },
          {
            "id": "7fb4a5c4c8371e17",
            "type": "leaf",
            "state": {
              "type": "bookmarks",
              "state": {}
            }
          }
        ]
      },
      {
        "id": "66820b311047e90e",
        "type": "tabs",
        "dimension": 19.676945668135097,
        "children": [
          {
            "id": "b8d2df7aea0a47c5",
            "type": "leaf",
            "state": {
              "type": "recent-files",
              "state": {}
            }
          }
        ]
      }
    ],
    "direction": "horizontal",
    "width": 307.5
  },
  "right": {
    "id": "1ca23899daf6fc57",
    "type": "split",
    "children": [
      {
        "id": "8baae523013a5ec8",
        "type": "tabs",
        "children": [
          {
            "id": "dc388f31586f5d92",
            "type": "leaf",
            "state": {
              "type": "backlink",
              "state": {
                "file": "深度学习/计算机视觉.md",
                "collapseAll": false,
                "extraContext": false,
                "sortOrder": "alphabetical",
                "showSearch": false,
                "searchQuery": "",
                "backlinkCollapsed": false,
                "unlinkedCollapsed": true
              }
            }
          },
          {
            "id": "d0e86a238026daab",
            "type": "leaf",
            "state": {
              "type": "outgoing-link",
              "state": {
                "file": "深度学习/计算机视觉.md",
                "linksCollapsed": false,
                "unlinkedCollapsed": true
              }
            }
          },
          {
            "id": "9d73979f88315024",
            "type": "leaf",
            "state": {
              "type": "tag",
              "state": {
                "sortOrder": "frequency",
                "useHierarchy": false
              }
            }
          },
          {
            "id": "00363296747ac1a9",
            "type": "leaf",
            "state": {
              "type": "quiet-outline",
              "state": {}
            }
          },
          {
            "id": "6b4f188967ced353",
            "type": "leaf",
            "state": {
              "type": "outline",
              "state": {
                "file": "深度学习/计算机视觉.md"
              }
            }
          }
        ],
        "currentTab": 3
      }
    ],
    "direction": "horizontal",
    "width": 301.5
  },
  "left-ribbon": {
    "hiddenItems": {
      "switcher:打开快速切换": false,
      "graph:查看关系图谱": false,
      "canvas:新建白板": false,
      "daily-notes:打开/创建今天的日记": false,
      "templates:插入模板": false,
      "command-palette:打开命令面板": false,
      "random-note:开始漫游笔记": false
    }
  },
  "active": "850e2ae8dd7226b7",
  "lastOpenFiles": [
    "image/Pasted image 20230801115153.png",
    "image/Pasted image 20230801114059.png",
    "image/Pasted image 20230801114028.png",
    "image/Pasted image 20230731181915.png",
    "深度学习/卷积神经网络.md",
    "实践经验/混淆矩阵.md",
    "深度学习/未命名.md",
    "强化学习/动态规划算法.md",
    "深度学习/多层感知机.md",
    "实践经验/数据预处理专题.md",
    "image/Pasted image 20230731111732.png",
    "实践经验",
    "深度学习/计算机视觉.md",
    "深度学习/现代卷积神经网络.md",
    "深度学习/现代循环神经网络.md",
    "image/Pasted image 20230731000300.png",
    "image/Pasted image 20230731000140.png",
    "image/Pasted image 20230731000133.png",
    "image/Pasted image 20230730235927.png",
    "image/output.png",
    "image/output 2.svg",
    "深度学习/注意力机制.md",
    "深度学习/预备知识.md",
    "深度学习/循环神经网络.md",
    "思维.canvas",
    "矩阵分析/矩阵函数/矩阵级数.md",
    "机器学习/k 近邻.md",
    "机器学习/条件随机场.md",
    "最优化/搜索算法/登山搜索.md",
    "2023-05-23.md",
    "随机过程/随机过程.md",
    "随机过程/更新过程.md",
    "随机过程/随机过程准备知识.md",
    "随机过程/随机过程课本笔记.md",
    "随机过程/条件期望.md",
    "随机过程/Brown运动.md",
    "随机过程/Markov链.md",
    "随机过程/随机过程讲义.pdf",
    "随机过程/讲解.md",
    "new/随机过程/随机过程讲义.pdf",
    "new/随机过程",
    "new/image/utils.py",
    "new/image",
    "new",
    "数据库.canvas",
    "image/utils.py",
    "深度学习/未命名",
    "随机过程/作业",
    "最优化/群体智能算法/未命名.canvas",
    "矩阵分析/未命名.canvas"
  ]
}